raymics/__init__.py
raymics/constants.py
raymics/dataset.py
raymics/extract_radiomics_features.py
raymics/log.py
raymics/task.py
raymics/utils.py
raymics-0.7.5.dist-info/METADATA
raymics-0.7.5.dist-info/WHEEL
raymics-0.7.5.dist-info/top_level.txt
raymics-0.7.5.dist-info/RECORD
