Metadata-Version: 2.1
Name: raymics
Version: 0.7.5
Summary: Raymics Tools
Requires-Dist: numpy (==1.23.5)
Requires-Dist: pandas (==1.5.3)
Requires-Dist: tqdm (==4.65.0)
Requires-Dist: imageio (==2.27.0)
Requires-Dist: imageio-ffmpeg (==0.4.8)
Requires-Dist: av (==10.0.0)
Requires-Dist: SimpleITK (==2.2.1)
Requires-Dist: pyradiomics (==3.0.1)
Requires-Dist: opencv-contrib-python (==4.7.0.72)
Requires-Dist: dicom2nifti (==2.4.8)
Requires-Dist: tsfresh (==0.20.0)
Requires-Dist: trimesh (==3.23.5)
Requires-Dist: scipy (==1.11.1)
Requires-Dist: scikit-image (==0.21.0)
